JuliaPythonAdaptor/__init__.py
JuliaPythonAdaptor-0.3.0.dist-info/LICENSE
JuliaPythonAdaptor-0.3.0.dist-info/METADATA
JuliaPythonAdaptor-0.3.0.dist-info/WHEEL
JuliaPythonAdaptor-0.3.0.dist-info/top_level.txt
JuliaPythonAdaptor-0.3.0.dist-info/RECORD
