Metadata-Version: 2.1
Name: JuliaPythonAdaptor
Version: 0.3.0
Summary: UNKNOWN
Home-page: https://github.com/thautwarm/JuliaPythonAdaptor
Author: thautwarm
Author-email: twshere@outlook.com
License: mit
Platform: any
Classifier: Programming Language :: Python :: 3.7
Classifier: Programming Language :: Python :: 3.8
Classifier: Programming Language :: Python :: 3.9
Classifier: Programming Language :: Python :: 3.10
Classifier: Programming Language :: Python :: Implementation :: CPython
Requires-Python: >=3.7.0
License-File: LICENSE
Requires-Dist: juliacall (>=0.9.3)
